artd_colombian_cities/__init__.py
artd_colombian_cities/asgi.py
artd_colombian_cities/settings.py
artd_colombian_cities/urls.py
artd_colombian_cities/wsgi.py
colombian_cities/__init__.py
colombian_cities/admin.py
colombian_cities/apps.py
colombian_cities/models.py
colombian_cities/tests.py
colombian_cities/views.py
colombian_cities/data/cities.py
colombian_cities/data/countries.py
colombian_cities/data/regions.py
colombian_cities/generators/generators.py
colombian_cities/management/commands/__init__.py
colombian_cities/management/commands/create_colombian_cities.py
colombian_cities/management/commands/create_colombian_regions.py
colombian_cities/management/commands/create_countries.py
colombian_cities/migrations/0001_initial.py
colombian_cities/migrations/__init__.py
migrate/__init__.py
migrate/admin.py
migrate/apps.py
migrate/models.py
migrate/tests.py
migrate/views.py
migrate/migrations/__init__.py
artd_colombian_cities-0.0.17.dist-info/METADATA
artd_colombian_cities-0.0.17.dist-info/WHEEL
artd_colombian_cities-0.0.17.dist-info/top_level.txt
artd_colombian_cities-0.0.17.dist-info/RECORD
